AUTHORS
Changelog
INSTALL
LICENSE
MANIFEST.in
README
README.rst
THANKS
TODO
setup.cfg
setup.py
callme/__init__.py
callme/base.py
callme/exceptions.py
callme/protocol.py
callme/proxy.py
callme/server.py
callme/test.py
callme.egg-info/PKG-INFO
callme.egg-info/SOURCES.txt
callme.egg-info/dependency_links.txt
callme.egg-info/requires.txt
callme.egg-info/top_level.txt
callme.egg-info/zip-safe
callme/tests/integration/test_actions.py
callme/tests/unit/test_protocol.py
callme/tests/unit/test_proxy.py
callme/tests/unit/test_server.py
doc/Makefile
doc/source/Changelog.rst
doc/source/conf.py
doc/source/develop.rst
doc/source/index.rst
doc/source/introduction.rst
doc/source/proxy.rst
doc/source/server.rst